{"run_number": "1698838055672475", "step_name": "start", "task_id": "1", "attempt_id": 0, "name": "_graph_info", "content_type": "gzip+pickle-v2", "type": "metaflow.artifact", "sha": "90f6be90f2ceaec0f0915633bde41d795cd14599", "ds_type": "local", "location": ":root:/Users/sakshamgulati/MLOps_Template/.metaflow", "flow_id": "HelloWorldFlow", "user_name": "sakshamgulati", "tags": [], "system_tags": ["runtime:dev", "user:sakshamgulati", "python_version:3.10.1", "metaflow_version:2.10.5"], "ts_epoch": 1698838055822}